hogwarts_browser_use/__init__.py
hogwarts_browser_use/model/__init__.py
hogwarts_browser_use/model/task.py
hogwarts_browser_use/service/__init__.py
hogwarts_browser_use/service/__main__.py
hogwarts_browser_use/service/chrome_debug.py
hogwarts_browser_use/service/controller.py
hogwarts_browser_use/service/core.py
hogwarts_browser_use/service/llm_factory.py
hogwarts_browser_use/tests/__init__.py
hogwarts_browser_use/tests/it/__init__.py
hogwarts_browser_use/tests/it/test_agent.py
hogwarts_browser_use-0.1.1.dist-info/METADATA
hogwarts_browser_use-0.1.1.dist-info/WHEEL
hogwarts_browser_use-0.1.1.dist-info/entry_points.txt
hogwarts_browser_use-0.1.1.dist-info/top_level.txt
hogwarts_browser_use-0.1.1.dist-info/RECORD
