Metadata-Version: 2.2
Name: hogwarts-browser-use
Version: 0.1.1
Summary: hogwarts browser use 霍格沃兹测试开发学社学员定制版
Author: 霍格沃兹测试开发学社
Project-URL: Homepage, https://ceshiren.com
Requires-Python: >=3.11
Requires-Dist: aiohappyeyeballs==2.4.4
Requires-Dist: aiohttp==3.11.11
Requires-Dist: aiosignal==1.3.2
Requires-Dist: annotated-types==0.7.0
Requires-Dist: anthropic==0.43.1
Requires-Dist: anyio==4.8.0
Requires-Dist: argparse==1.4.0
Requires-Dist: attrs==24.3.0
Requires-Dist: babel==2.16.0
Requires-Dist: backoff==2.2.1
Requires-Dist: beautifulsoup4==4.12.3
Requires-Dist: boto3==1.36.2
Requires-Dist: botocore==1.36.2
Requires-Dist: browser-use==0.1.26
Requires-Dist: cachetools==5.5.0
Requires-Dist: certifi==2024.12.14
Requires-Dist: charset-normalizer==3.4.1
Requires-Dist: click==8.1.8
Requires-Dist: courlan==1.3.2
Requires-Dist: dateparser==1.2.0
Requires-Dist: defusedxml==0.7.1
Requires-Dist: deprecated==1.2.15
Requires-Dist: distro==1.9.0
Requires-Dist: filetype==1.2.0
Requires-Dist: fireworks-ai==0.15.11
Requires-Dist: frozenlist==1.5.0
Requires-Dist: google-ai-generativelanguage==0.6.10
Requires-Dist: google-api-core[grpc]==2.24.0
Requires-Dist: google-api-python-client==2.159.0
Requires-Dist: google-auth==2.37.0
Requires-Dist: google-auth-httplib2==0.2.0
Requires-Dist: google-generativeai==0.8.3
Requires-Dist: googleapis-common-protos==1.66.0
Requires-Dist: greenlet==3.1.1
Requires-Dist: grpcio==1.69.0
Requires-Dist: grpcio-status==1.69.0
Requires-Dist: h11==0.14.0
Requires-Dist: html2text==2024.2.26
Requires-Dist: htmldate==1.9.3
Requires-Dist: httpcore==1.0.7
Requires-Dist: httplib2==0.22.0
Requires-Dist: httpx==0.27.2
Requires-Dist: httpx-sse==0.4.0
Requires-Dist: httpx-ws==0.7.1
Requires-Dist: idna==3.10
Requires-Dist: importlib-metadata==8.5.0
Requires-Dist: jiter==0.8.2
Requires-Dist: jmespath==1.0.1
Requires-Dist: jsonpatch==1.33
Requires-Dist: jsonpointer==3.0.0
Requires-Dist: justext==3.0.1
Requires-Dist: langchain==0.3.14
Requires-Dist: langchain-anthropic==0.3.3
Requires-Dist: langchain-aws==0.2.11
Requires-Dist: langchain-core==0.3.30
Requires-Dist: langchain-fireworks==0.2.6
Requires-Dist: langchain-google-genai==2.0.8
Requires-Dist: langchain-ollama==0.2.2
Requires-Dist: langchain-openai==0.3.1
Requires-Dist: langchain-text-splitters==0.3.5
Requires-Dist: langsmith==0.2.11
Requires-Dist: lmnr[langchain]==0.4.54
Requires-Dist: lxml[html-clean]==5.3.0
Requires-Dist: lxml-html-clean==0.4.1
Requires-Dist: maincontentextractor==0.0.4
Requires-Dist: monotonic==1.6
Requires-Dist: multidict==6.1.0
Requires-Dist: numpy==1.26.4
Requires-Dist: ollama==0.4.6
Requires-Dist: openai==1.59.9
Requires-Dist: opentelemetry-api==1.29.0
Requires-Dist: opentelemetry-exporter-otlp-proto-common==1.29.0
Requires-Dist: opentelemetry-exporter-otlp-proto-grpc==1.29.0
Requires-Dist: opentelemetry-exporter-otlp-proto-http==1.29.0
Requires-Dist: opentelemetry-instrumentation==0.50b0
Requires-Dist: opentelemetry-instrumentation-langchain==0.36.1
Requires-Dist: opentelemetry-instrumentation-requests==0.50b0
Requires-Dist: opentelemetry-instrumentation-sqlalchemy==0.50b0
Requires-Dist: opentelemetry-instrumentation-threading==0.50b0
Requires-Dist: opentelemetry-instrumentation-urllib3==0.50b0
Requires-Dist: opentelemetry-proto==1.29.0
Requires-Dist: opentelemetry-sdk==1.29.0
Requires-Dist: opentelemetry-semantic-conventions==0.50b0
Requires-Dist: opentelemetry-semantic-conventions-ai==0.4.2
Requires-Dist: opentelemetry-util-http==0.50b0
Requires-Dist: orjson==3.10.15
Requires-Dist: packaging==24.2
Requires-Dist: pillow==11.1.0
Requires-Dist: playwright==1.49.1
Requires-Dist: posthog==3.8.4
Requires-Dist: propcache==0.2.1
Requires-Dist: proto-plus==1.25.0
Requires-Dist: protobuf==5.29.3
Requires-Dist: pyasn1==0.6.1
Requires-Dist: pyasn1-modules==0.4.1
Requires-Dist: pydantic==2.10.5
Requires-Dist: pydantic-core==2.27.2
Requires-Dist: pyee==12.0.0
Requires-Dist: pyparsing==3.2.1
Requires-Dist: python-dateutil==2.9.0.post0
Requires-Dist: python-dotenv==1.0.1
Requires-Dist: pytz==2024.2
Requires-Dist: pyyaml==6.0.2
Requires-Dist: regex==2024.11.6
Requires-Dist: requests==2.32.3
Requires-Dist: requests-toolbelt==1.0.0
Requires-Dist: rsa==4.9
Requires-Dist: s3transfer==0.11.1
Requires-Dist: six==1.17.0
Requires-Dist: sniffio==1.3.1
Requires-Dist: soupsieve==2.6
Requires-Dist: sqlalchemy==2.0.37
Requires-Dist: tenacity==9.0.0
Requires-Dist: tiktoken==0.8.0
Requires-Dist: tld==0.13
Requires-Dist: tqdm==4.67.1
Requires-Dist: trafilatura==2.0.0
Requires-Dist: typing-extensions==4.12.2
Requires-Dist: tzlocal==5.2
Requires-Dist: uritemplate==4.1.1
Requires-Dist: urllib3==2.3.0
Requires-Dist: wrapt==1.17.2
Requires-Dist: wsproto==1.2.0
Requires-Dist: yarl==1.18.3
Requires-Dist: zipp==3.21.0
